optivision/__init__.py
optivision/common.py
optivision/connectivity/__init__.py
optivision/connectivity/connected_components.py
optivision/quantization/__init__.py
optivision/quantization/reduce_gray_levels.py
optivision/quantization/to_binary.py
optivision/transformations/__init__.py
optivision/transformations/gamma.py
optivision/transformations/logarithmic.py
optivision/transformations/negative.py
optivision-0.3.0.dist-info/LICENSE
optivision-0.3.0.dist-info/METADATA
optivision-0.3.0.dist-info/WHEEL
optivision-0.3.0.dist-info/RECORD
