Metadata-Version: 2.1
Name: optivision
Version: 0.3.0
Summary: Simple Image Processing Library
Author: Preet Sojitra
Requires-Python: >=3.8,<4.0
Classifier: Programming Language :: Python :: 3
Classifier: Programming Language :: Python :: 3.8
Classifier: Programming Language :: Python :: 3.9
Classifier: Programming Language :: Python :: 3.10
Classifier: Programming Language :: Python :: 3.11
Classifier: Programming Language :: Python :: 3.12
Requires-Dist: numpy (>=1.19.2,<2.0.0)
